customized_chart/__init__.py
customized_chart/customized_chart.py
customized_chart-0.1.22.dist-info/LICENSE
customized_chart-0.1.22.dist-info/METADATA
customized_chart-0.1.22.dist-info/WHEEL
customized_chart-0.1.22.dist-info/top_level.txt
customized_chart-0.1.22.dist-info/RECORD
